map_closures/pybind/etc/haarcascades/haarcascade_eye.xml
map_closures/pybind/etc/haarcascades/haarcascade_eye_tree_eyeglasses.xml
map_closures/pybind/etc/haarcascades/haarcascade_frontalcatface.xml
map_closures/pybind/etc/haarcascades/haarcascade_frontalcatface_extended.xml
map_closures/pybind/etc/haarcascades/haarcascade_frontalface_alt.xml
map_closures/pybind/etc/haarcascades/haarcascade_frontalface_alt2.xml
map_closures/pybind/etc/haarcascades/haarcascade_frontalface_alt_tree.xml
map_closures/pybind/etc/haarcascades/haarcascade_frontalface_default.xml
map_closures/pybind/etc/haarcascades/haarcascade_fullbody.xml
map_closures/pybind/etc/haarcascades/haarcascade_lefteye_2splits.xml
map_closures/pybind/etc/haarcascades/haarcascade_license_plate_rus_16stages.xml
map_closures/pybind/etc/haarcascades/haarcascade_lowerbody.xml
map_closures/pybind/etc/haarcascades/haarcascade_profileface.xml
map_closures/pybind/etc/haarcascades/haarcascade_righteye_2splits.xml
map_closures/pybind/etc/haarcascades/haarcascade_russian_plate_number.xml
map_closures/pybind/etc/haarcascades/haarcascade_smile.xml
map_closures/pybind/etc/haarcascades/haarcascade_upperbody.xml
map_closures/pybind/etc/lbpcascades/lbpcascade_frontalcatface.xml
map_closures/pybind/etc/lbpcascades/lbpcascade_frontalface.xml
map_closures/pybind/etc/lbpcascades/lbpcascade_frontalface_improved.xml
map_closures/pybind/etc/lbpcascades/lbpcascade_profileface.xml
map_closures/pybind/etc/lbpcascades/lbpcascade_silverware.xml
map_closures/pybind/etc/licenses/ade-LICENSE
map_closures/pybind/etc/licenses/ffmpeg-license.txt
map_closures/pybind/etc/licenses/ffmpeg-readme.txt
map_closures/pybind/etc/licenses/flatbuffers-LICENSE.txt
map_closures/pybind/etc/licenses/ippicv-EULA.rtf
map_closures/pybind/etc/licenses/ippicv-readme.htm
map_closures/pybind/etc/licenses/ippicv-third-party-programs.txt
map_closures/pybind/etc/licenses/ippiw-EULA.rtf
map_closures/pybind/etc/licenses/ippiw-support.txt
perceptual_map_closures-2.0.3.dist-info/METADATA
perceptual_map_closures-2.0.3.dist-info/WHEEL
perceptual_map_closures-2.0.3.dist-info/entry_points.txt
perceptual_map_closures-2.0.3.dist-info/licenses/LICENSE
perceptual_map_closures-2.0.3.dist-info/RECORD
